edhelper/__init__.py
edhelper/main.py
edhelper/cli/__init__.py
edhelper/cli/card.py
edhelper/cli/deck.py
edhelper/cli/export.py
edhelper/cli/utils.py
edhelper/commom/__init__.py
edhelper/commom/card_commands.py
edhelper/commom/commander_meta_commands.py
edhelper/commom/deck_analyzer.py
edhelper/commom/deck_card_commands.py
edhelper/commom/deck_commands.py
edhelper/commom/deck_list_commands.py
edhelper/commom/exception_handler.py
edhelper/commom/excptions.py
edhelper/commom/sync_db_commands.py
edhelper/commom/top_commanders_commands.py
edhelper/commom/utils.py
edhelper/commom/validators.py
edhelper/domain/__init__.py
edhelper/domain/card.py
edhelper/domain/card_service.py
edhelper/domain/deck.py
edhelper/domain/deck_card.py
edhelper/domain/deck_card_service.py
edhelper/domain/deck_service.py
edhelper/editor/backend/main.py
edhelper/editor/backend/app/routers/card.py
edhelper/editor/backend/app/routers/commander.py
edhelper/editor/backend/app/routers/deck.py
edhelper/editor/backend/app/schemas/card.py
edhelper/editor/backend/app/schemas/deck.py
edhelper/editor/backend/app/schemas/deck_cards.py
edhelper/editor/frontend/dist/index.html
edhelper/editor/frontend/dist/mock.txt
edhelper/editor/frontend/dist/vite.svg
edhelper/editor/frontend/dist/assets/index-CRjdcG1f.css
edhelper/editor/frontend/dist/assets/index-DrYlPGsp.js
edhelper/external/__init__.py
edhelper/external/api.py
edhelper/external/edhec.py
edhelper/infra/__init__.py
edhelper/infra/config.py
edhelper/infra/db.py
edhelper/infra/init_db.py
edhelper/infra/schema.sql
edhelper/shell/__init__.py
edhelper/shell/lang/__init__.py
edhelper/shell/lang/grammar.lark
edhelper/shell/lang/parser.py
edhelper/shell/lang/transformer.py
edhelper/shell/lang/commands/__init__.py
edhelper/shell/lang/commands/add.py
edhelper/shell/lang/commands/analyze.py
edhelper/shell/lang/commands/base.py
edhelper/shell/lang/commands/clear_screen.py
edhelper/shell/lang/commands/commander.py
edhelper/shell/lang/commands/copy.py
edhelper-0.3.0.dist-info/licenses/LICENSE
edhelper-0.3.0.dist-info/METADATA
edhelper-0.3.0.dist-info/WHEEL
edhelper-0.3.0.dist-info/entry_points.txt
edhelper-0.3.0.dist-info/top_level.txt
edhelper-0.3.0.dist-info/RECORD
