Metadata-Version: 2.4
Name: edhelper
Version: 0.3.0
Summary: EDH deck builder & analyzer with CLI, shell, and web editor
Author-email: Your Name <your.email@example.com>
License: MIT
Keywords: mtg,magic,commander,edh,deck,builder
Classifier: Development Status :: 3 - Alpha
Classifier: Intended Audience :: Developers
Classifier: License :: OSI Approved :: MIT License
Classifier: Programming Language :: Python :: 3
Classifier: Programming Language :: Python :: 3.12
Requires-Python: <3.13,>=3.12
License-File: LICENSE
Requires-Dist: click<9.0.0,>=8.1.7
Requires-Dist: httpx<1.0.0,>=0.27.0
Requires-Dist: requests<3.0.0,>=2.31.0
Requires-Dist: python-dotenv<2.0.0,>=1.0.1
Requires-Dist: keyring<26.0.0,>=24.3.0
Requires-Dist: tabulate<1.0.0,>=0.9.0
Provides-Extra: shell
Requires-Dist: lark<2.0.0,>=1.1.9; extra == "shell"
Requires-Dist: prompt-toolkit<4.0.0,>=3.0.43; extra == "shell"
Requires-Dist: pygments<3.0.0,>=2.17.0; extra == "shell"
Provides-Extra: editor
Requires-Dist: fastapi<0.111.0,>=0.110.0; extra == "editor"
Requires-Dist: uvicorn<1.0.0,>=0.29.0; extra == "editor"
Requires-Dist: python-multipart<1.0.0,>=0.0.9; extra == "editor"
Provides-Extra: all
Requires-Dist: lark<2.0.0,>=1.1.9; extra == "all"
Requires-Dist: prompt-toolkit<4.0.0,>=3.0.43; extra == "all"
Requires-Dist: pygments<3.0.0,>=2.17.0; extra == "all"
Requires-Dist: fastapi<0.111.0,>=0.110.0; extra == "all"
Requires-Dist: uvicorn<1.0.0,>=0.29.0; extra == "all"
Requires-Dist: python-multipart<1.0.0,>=0.0.9; extra == "all"
Dynamic: license-file
